Metadata-Version: 2.1
Name: pennylane-qrack-cpu
Version: 0.26.0
Summary: PennyLane plugin for Qrack.
Home-page: http://github.com/vm6502q
Maintainer: vm6502q
Maintainer-email: stranoj@gmail.com
License: Apache License 2.0
Classifier: Development Status :: 4 - Beta
Classifier: Environment :: Console
Classifier: Intended Audience :: Science/Research
Classifier: License :: OSI Approved :: Apache Software License
Classifier: Natural Language :: English
Classifier: Operating System :: POSIX
Classifier: Operating System :: MacOS :: MacOS X
Classifier: Operating System :: POSIX :: Linux
Classifier: Operating System :: Microsoft :: Windows
Classifier: Programming Language :: Python
Classifier: Programming Language :: Python :: 3
Classifier: Programming Language :: Python :: 3.9
Classifier: Programming Language :: Python :: 3.10
Classifier: Programming Language :: Python :: 3.11
Classifier: Programming Language :: Python :: 3.12
Classifier: Programming Language :: Python :: 3 :: Only
Classifier: Topic :: Scientific/Engineering :: Quantum Computing
Provides: pennylane_qrack
License-File: LICENSE
Requires-Dist: pennylane>=0.39.0
Requires-Dist: pyqrack-cpu>=1.30.0
Requires-Dist: numpy>=1.16
